english_dictionary/__init__.py
english_dictionary/data/dict_pkl
english_dictionary/scripts/__init__.py
english_dictionary/scripts/build_dictionary.py
english_dictionary/scripts/dict.pickle
english_dictionary/scripts/dict.pkl
english_dictionary/scripts/dict_pkl
english_dictionary/scripts/get_dict
english_dictionary/scripts/read_pickle.py
english_dictionary/scripts/scrape_merriam_webster.py
english_dictionary/scripts/test.py
english_dictionary/scripts/tokenize.py
english_dictionary/scripts/write_pickle.py
english_dictionary/tools/get_words.sh
english_dictionary/tools/words.txt
english_dictionary-1.0.24.dist-info/LICENSE
english_dictionary-1.0.24.dist-info/METADATA
english_dictionary-1.0.24.dist-info/WHEEL
english_dictionary-1.0.24.dist-info/entry_points.txt
english_dictionary-1.0.24.dist-info/top_level.txt
english_dictionary-1.0.24.dist-info/RECORD
