Metadata-Version: 2.1
Name: english_dictionary
Version: 1.0.24
Summary: In-memory dictionary of 100 thousand English words
Home-page: https://github.com/DanDelluomo/dictionary
Author: Daniel E. Dell'uomo
Author-email: dandelluomo@gmail.com
License: MIT
Platform: UNKNOWN
Classifier: License :: OSI Approved :: MIT License
Classifier: Programming Language :: Python :: 3
Classifier: Programming Language :: Python :: 3.7
